prefetch2es/__init__.py
prefetch2es/models/ElasticsearchUtils.py
prefetch2es/models/MetaData.py
prefetch2es/models/Prefetch2es.py
prefetch2es/presenters/Prefetch2esPresenter.py
prefetch2es/presenters/Prefetch2jsonPresenter.py
prefetch2es/views/BaseView.py
prefetch2es/views/Prefetch2esView.py
prefetch2es/views/Prefetch2jsonView.py
prefetch2es-2.2.2.dist-info/METADATA
prefetch2es-2.2.2.dist-info/WHEEL
prefetch2es-2.2.2.dist-info/entry_points.txt
prefetch2es-2.2.2.dist-info/licenses/LICENSE
prefetch2es-2.2.2.dist-info/licenses/LICENSE.LESSER
prefetch2es-2.2.2.dist-info/RECORD
