Metadata-Version: 2.4
Name: prefetch2es
Version: 2.2.2
Summary: A library for fast parse & import of Windows Prefetch into Elasticsearch.
Author-email: sumeshi <sum3sh1@protonmail.com>
License-Expression: LGPL-3.0-or-later
License-File: LICENSE
License-File: LICENSE.LESSER
Requires-Python: >=3.11
Requires-Dist: elasticsearch>=9.0.2
Requires-Dist: libscca-python==20240215
Requires-Dist: orjson>=3.10.18
Requires-Dist: tqdm>=4.67.1
Requires-Dist: urllib3>=2.5.0
